fapylib/__init__.py
fapylib/app.py
fapylib/apr.py
fapylib/cfg.py
fapylib/dbs.py
fapylib/mig.py
fapylib/sap.py
fapylib/utl.py
fapylib-0.1.11.dist-info/METADATA
fapylib-0.1.11.dist-info/WHEEL
fapylib-0.1.11.dist-info/RECORD
